{
  "metadata": {
    "permit_id": "b20efcdf-3359-4e49-afc9-4dfb61a68e49",
    "permit_number": "RBPR-144560-2025",
    "status": "Issued",
    "permit_data": {
      "permit": {
        "Value": 665000,
        "PermitId": "b20efcdf-3359-4e49-afc9-4dfb61a68e49",
        "ApplyDate": "2025-04-07T15:04:40.243Z",
        "IVRNumber": "250384",
        "IssueDate": "2025-04-22T12:34:00Z",
        "AssignedTo": "Bower, Rose",
        "ExpireDate": "2026-08-31T17:12:27Z",
        "PermitType": "Residential - New One- and Two-Family Dwelling",
        "SquareFeet": 0,
        "Description": "Kalas Falls PH 1, Lot 28 - 2 Story Single-Family Home  on Crawlspace, 3133 Sq Ft Conditioned Space with 438 Sq Ft Garage, 4 Bedroom(s), 3 Bath(s), Front & Rear Porch, No Deck, 1 Fireplace(s), Note: [none]",
        "MainAddress": "1132 DARTFORD GREEN PL \r\nWAKE FOREST, 27587",
        "ProjectName": null,
        "DistrictName": "Rolesville",
        "FinalizeDate": null,
        "PermitNumber": "RBPR-144560-2025",
        "PermitStatus": "Issued",
        "WorkClassName": "New One- and Two-Family Dwelling",
        "AssignedToEmail": "rbower@rolesvillenc.gov",
        "MainAddressInfo": {
          "City": "WAKE FOREST",
          "State": null,
          "County": null,
          "Country": null,
          "PostalCode": "27587",
          "StreetType": "PL",
          "AddressLine1": "1132",
          "AddressLine2": "DARTFORD GREEN",
          "AddressLine3": null
        },
        "MainParcelNumber": "1767390585"
      },
      "summary": {
        "Result": [
          {
            "Name": "Issue Permit",
            "Status": 0,
            "CompletedOn": null,
            "ActivityType": "CreateReport",
            "FriendlyName": "Issue Permit",
            "ActivityTypeName": "Create Report",
            "ActivityStatusName": null,
            "ScheduledStartDate": null
          },
          {
            "Name": "WM - S&E Control Permit",
            "Status": 0,
            "CompletedOn": "2022-06-01T15:54:42Z",
            "ActivityType": "CreateSubPermit",
            "FriendlyName": "WM - S&E Control Permit",
            "ActivityTypeName": "Permit",
            "ActivityStatusName": null,
            "ScheduledStartDate": null
          },
          {
            "Name": "Application Review",
            "Status": 0,
            "CompletedOn": "2025-04-10T04:00:00Z",
            "ActivityType": "ReceiveSubmittal",
            "FriendlyName": "Application Review",
            "ActivityTypeName": "Submittal",
            "ActivityStatusName": null,
            "ScheduledStartDate": null
          },
          {
            "Name": "Residential Plan Review",
            "Status": 0,
            "CompletedOn": "2025-04-16T04:00:00Z",
            "ActivityType": "ReceiveSubmittal",
            "FriendlyName": "Residential Plan Review",
            "ActivityTypeName": "Submittal",
            "ActivityStatusName": null,
            "ScheduledStartDate": null
          },
          {
            "Name": "P&I - Footing or Monolithic Slab",
            "Status": 0,
            "CompletedOn": "2025-05-07T13:01:14.057Z",
            "ActivityType": "Inspection",
            "FriendlyName": "P&I - Footing or Monolithic Slab",
            "ActivityTypeName": "Inspection",
            "ActivityStatusName": "Passed",
            "ScheduledStartDate": "2025-05-07T04:00:00Z"
          },
          {
            "Name": "P&I - Foundation",
            "Status": 0,
            "CompletedOn": "2025-05-08T13:06:15.87Z",
            "ActivityType": "Inspection",
            "FriendlyName": "P&I - Foundation",
            "ActivityTypeName": "Inspection",
            "ActivityStatusName": "Passed",
            "ScheduledStartDate": "2025-05-08T04:00:00Z"
          },
          {
            "Name": "P&I - Floor Framing",
            "Status": 0,
            "CompletedOn": "2025-05-08T13:12:32.78Z",
            "ActivityType": "Inspection",
            "FriendlyName": "P&I - Floor Framing",
            "ActivityTypeName": "Inspection",
            "ActivityStatusName": "Passed",
            "ScheduledStartDate": "2025-05-08T13:00:00Z"
          },
          {
            "Name": "P&I - Plumbing Rough",
            "Status": 0,
            "CompletedOn": "2025-05-21T17:38:38.907Z",
            "ActivityType": "Inspection",
            "FriendlyName": "P&I - Plumbing Rough",
            "ActivityTypeName": "Inspection",
            "ActivityStatusName": "Passed",
            "ScheduledStartDate": "2025-05-21T04:00:00Z"
          },
          {
            "Name": "P&I - Mechanical Rough",
            "Status": 3,
            "CompletedOn": "2025-05-22T11:52:09.543Z",
            "ActivityType": "Inspection",
            "FriendlyName": "P&I - Mechanical Rough",
            "ActivityTypeName": "Inspection",
            "ActivityStatusName": "Re-inspection required with fee - Permit",
            "ScheduledStartDate": "2025-05-22T04:00:00Z"
          },
          {
            "Name": "P&I - Mechanical Rough",
            "Status": 0,
            "CompletedOn": "2025-05-23T17:41:48.007Z",
            "ActivityType": "Inspection",
            "FriendlyName": "P&I - Mechanical Rough",
            "ActivityTypeName": "Inspection",
            "ActivityStatusName": "Passed",
            "ScheduledStartDate": "2025-05-23T04:00:00Z"
          },
          {
            "Name": "P&I - Electrical Rough",
            "Status": 0,
            "CompletedOn": "2025-05-27T15:32:41.817Z",
            "ActivityType": "Inspection",
            "FriendlyName": "P&I - Electrical Rough",
            "ActivityTypeName": "Inspection",
            "ActivityStatusName": "Passed",
            "ScheduledStartDate": "2025-05-27T04:00:00Z"
          },
          {
            "Name": "P&I - Framing",
            "Status": 0,
            "CompletedOn": "2025-05-28T14:41:15.607Z",
            "ActivityType": "Inspection",
            "FriendlyName": "P&I - Framing",
            "ActivityTypeName": "Inspection",
            "ActivityStatusName": "Passed with Conditions",
            "ScheduledStartDate": "2025-05-28T04:00:00Z"
          },
          {
            "Name": "P&I - Insulation",
            "Status": 3,
            "CompletedOn": "2025-06-04T17:18:21.577Z",
            "ActivityType": "Inspection",
            "FriendlyName": "P&I - Insulation",
            "ActivityTypeName": "Inspection",
            "ActivityStatusName": "Re-inspection required with fee - Permit",
            "ScheduledStartDate": "2025-06-04T04:00:00Z"
          },
          {
            "Name": "P&I - Insulation",
            "Status": 0,
            "CompletedOn": "2025-06-06T14:43:56.893Z",
            "ActivityType": "Inspection",
            "FriendlyName": "P&I - Insulation",
            "ActivityTypeName": "Inspection",
            "ActivityStatusName": "Passed",
            "ScheduledStartDate": "2025-06-06T04:00:00Z"
          },
          {
            "Name": "P&I - Water Connection",
            "Status": 0,
            "CompletedOn": "2025-06-20T18:56:19.22Z",
            "ActivityType": "Inspection",
            "FriendlyName": "P&I - Water Connection",
            "ActivityTypeName": "Inspection",
            "ActivityStatusName": "Passed",
            "ScheduledStartDate": "2025-06-20T04:00:00Z"
          },
          {
            "Name": "P&I - Sewer Connection",
            "Status": 0,
            "CompletedOn": "2025-06-20T18:56:19.22Z",
            "ActivityType": "Inspection",
            "FriendlyName": "P&I - Sewer Connection",
            "ActivityTypeName": "Inspection",
            "ActivityStatusName": "Passed",
            "ScheduledStartDate": "2025-06-20T04:00:00Z"
          },
          {
            "Name": "P&I - Plumbing Groundwork",
            "Status": 0,
            "CompletedOn": "2025-06-20T18:56:19.23Z",
            "ActivityType": "Inspection",
            "FriendlyName": "P&I - Plumbing Groundwork",
            "ActivityTypeName": "Inspection",
            "ActivityStatusName": "Passed",
            "ScheduledStartDate": "2025-06-20T04:00:00Z"
          },
          {
            "Name": "P&I - Sewer Connection",
            "Status": 0,
            "CompletedOn": "2025-06-20T18:56:19.23Z",
            "ActivityType": "Inspection",
            "FriendlyName": "P&I - Sewer Connection",
            "ActivityTypeName": "Inspection",
            "ActivityStatusName": "Passed",
            "ScheduledStartDate": "2025-06-20T04:00:00Z"
          },
          {
            "Name": "P&I - Electrical Final",
            "Status": 0,
            "CompletedOn": "2025-07-11T12:48:05.533Z",
            "ActivityType": "Inspection",
            "FriendlyName": "P&I - Electrical Final",
            "ActivityTypeName": "Inspection",
            "ActivityStatusName": "Passed",
            "ScheduledStartDate": "2025-07-11T04:00:00Z"
          },
          {
            "Name": "P&I - Mechanical Final",
            "Status": 0,
            "CompletedOn": "2025-07-11T13:02:53.59Z",
            "ActivityType": "Inspection",
            "FriendlyName": "P&I - Mechanical Final",
            "ActivityTypeName": "Inspection",
            "ActivityStatusName": "Passed",
            "ScheduledStartDate": "2025-07-11T04:00:00Z"
          },
          {
            "Name": "P&I - Plumbing Final",
            "Status": 0,
            "CompletedOn": "2025-07-14T12:22:55.2Z",
            "ActivityType": "Inspection",
            "FriendlyName": "P&I - Plumbing Final",
            "ActivityTypeName": "Inspection",
            "ActivityStatusName": "Passed",
            "ScheduledStartDate": "2025-07-14T04:00:00Z"
          },
          {
            "Name": "P&I - Building Final",
            "Status": 0,
            "CompletedOn": "2025-08-29T17:12:45.443Z",
            "ActivityType": "Inspection",
            "FriendlyName": "P&I - Building Final",
            "ActivityTypeName": "Inspection",
            "ActivityStatusName": "Passed",
            "ScheduledStartDate": "2025-08-29T04:00:00Z"
          },
          {
            "Name": "Notify Utility Companies",
            "Status": 1,
            "CompletedOn": null,
            "ActivityType": "GenericAction",
            "FriendlyName": "Notify Utility Companies",
            "ActivityTypeName": "Generic Action",
            "ActivityStatusName": null,
            "ScheduledStartDate": null
          },
          {
            "Name": "Issue CO",
            "Status": 1,
            "CompletedOn": null,
            "ActivityType": "CreateReport",
            "FriendlyName": "Issue CO",
            "ActivityTypeName": "Create Report",
            "ActivityStatusName": null,
            "ScheduledStartDate": null
          }
        ]
      },
      "contacts": {
        "Result": [
          {
            "Title": "GC-29676-12/31/26",
            "LastName": "Davis",
            "FirstName": "Tracey",
            "IsBilling": true,
            "ContactStatus": "N/A",
            "ContactTypeName": "Applicant",
            "GlobalEntityName": "DR Horton INC",
            "IsBillingDisplayText": "Yes"
          },
          {
            "Title": "E-12915- 06/11/26",
            "LastName": "Allen",
            "FirstName": "Kat",
            "IsBilling": true,
            "ContactStatus": "Pending",
            "ContactTypeName": "Electrical Contractor",
            "GlobalEntityName": "Romanoff Electric Residential LLC",
            "IsBillingDisplayText": "Yes"
          },
          {
            "Title": "GC-29676-12/31/26",
            "LastName": "Davis",
            "FirstName": "Tracey",
            "IsBilling": false,
            "ContactStatus": "N/A",
            "ContactTypeName": "General Contractor",
            "GlobalEntityName": "DR Horton INC",
            "IsBillingDisplayText": "No"
          },
          {
            "Title": "H1,2,3 P1-17326  12-31-26  E-14471",
            "LastName": "Burns",
            "FirstName": "Melinda",
            "IsBilling": true,
            "ContactStatus": "N/A",
            "ContactTypeName": "Mechanical Contractor",
            "GlobalEntityName": "Weather Master Heating & Air Conditioning, Inc.",
            "IsBillingDisplayText": "Yes"
          },
          {
            "Title": "H1,2,3 P1-17326  12-31-26  E-14471",
            "LastName": "Burns",
            "FirstName": "Melinda",
            "IsBilling": true,
            "ContactStatus": "N/A",
            "ContactTypeName": "Plumbing Contractor",
            "GlobalEntityName": "Weather Master Heating & Air Conditioning, Inc.",
            "IsBillingDisplayText": "Yes"
          }
        ],
        "TotalFound": 5
      },
      "inspections": {
        "Result": [
          {
            "InspectionId": "f26ba1d9-34d5-4e78-be61-d50cec6d8cca",
            "RequestedDate": "2025-08-29T15:44:00Z",
            "InspectionType": "P&I - Building Final",
            "InspectionNumber": "824544-2025",
            "InspectionStatus": "Passed",
            "PrimaryInspector": "Alvarez Alex",
            "WorkflowActionId": null,
            "ScheduledStartDate": "2025-08-29T04:00:00Z",
            "PrimaryInspectorEmail": "alejandro.alvarez@wake.gov",
            "InspectionTypeDescription": "Building Final",
            "IsReinspectionDisplayText": "No"
          },
          {
            "InspectionId": "c84ee197-426c-455f-8039-acd67fa14f2c",
            "RequestedDate": "2025-07-11T16:37:43Z",
            "InspectionType": "P&I - Electrical Final",
            "InspectionNumber": "805091-2025",
            "InspectionStatus": "Passed",
            "PrimaryInspector": "Privette Emerson",
            "WorkflowActionId": null,
            "ScheduledStartDate": "2025-07-11T04:00:00Z",
            "PrimaryInspectorEmail": "emerson.privette@wake.gov",
            "InspectionTypeDescription": "Electrical Final",
            "IsReinspectionDisplayText": "No"
          },
          {
            "InspectionId": "3a991cb2-aa99-43ac-a709-7f9499dbb081",
            "RequestedDate": "2025-05-27T15:50:10Z",
            "InspectionType": "P&I - Electrical Rough",
            "InspectionNumber": "787194-2025",
            "InspectionStatus": "Passed",
            "PrimaryInspector": "Piratzky Andy",
            "WorkflowActionId": null,
            "ScheduledStartDate": "2025-05-27T04:00:00Z",
            "PrimaryInspectorEmail": "andy.piratzky@wake.gov",
            "InspectionTypeDescription": "Electrical Rough",
            "IsReinspectionDisplayText": "No"
          },
          {
            "InspectionId": "4a7ff7c4-1bfc-4f41-be67-3341e53f2ec9",
            "RequestedDate": "2025-05-08T04:00:00Z",
            "InspectionType": "P&I - Floor Framing",
            "InspectionNumber": "780794-2025",
            "InspectionStatus": "Passed",
            "PrimaryInspector": "McLaughlin Matthew",
            "WorkflowActionId": null,
            "ScheduledStartDate": "2025-05-08T13:00:00Z",
            "PrimaryInspectorEmail": "Matthew.McLaughlin@wake.gov",
            "InspectionTypeDescription": "Floor Framing",
            "IsReinspectionDisplayText": "No"
          },
          {
            "InspectionId": "48ec3839-2288-4252-9650-c7ec838e988d",
            "RequestedDate": "2025-05-07T16:08:06Z",
            "InspectionType": "P&I - Footing or Monolithic Slab",
            "InspectionNumber": "779839-2025",
            "InspectionStatus": "Passed",
            "PrimaryInspector": "Alvarez Alex",
            "WorkflowActionId": null,
            "ScheduledStartDate": "2025-05-07T04:00:00Z",
            "PrimaryInspectorEmail": "alejandro.alvarez@wake.gov",
            "InspectionTypeDescription": "Footing or Monolithic Slab",
            "IsReinspectionDisplayText": "No"
          },
          {
            "InspectionId": "ed9adc72-d14e-4373-9a2a-11a2ae971aad",
            "RequestedDate": "2025-05-08T16:02:35Z",
            "InspectionType": "P&I - Foundation",
            "InspectionNumber": "780376-2025",
            "InspectionStatus": "Passed",
            "PrimaryInspector": "McLaughlin Matthew",
            "WorkflowActionId": null,
            "ScheduledStartDate": "2025-05-08T04:00:00Z",
            "PrimaryInspectorEmail": "Matthew.McLaughlin@wake.gov",
            "InspectionTypeDescription": "Foundation",
            "IsReinspectionDisplayText": "No"
          },
          {
            "InspectionId": "48db665f-57da-4b8d-a22a-0642e9450b79",
            "RequestedDate": "2025-05-28T15:47:18Z",
            "InspectionType": "P&I - Framing",
            "InspectionNumber": "787767-2025",
            "InspectionStatus": "Passed with Conditions",
            "PrimaryInspector": "McLaughlin Matthew",
            "WorkflowActionId": null,
            "ScheduledStartDate": "2025-05-28T04:00:00Z",
            "PrimaryInspectorEmail": "Matthew.McLaughlin@wake.gov",
            "InspectionTypeDescription": "Framing",
            "IsReinspectionDisplayText": "No"
          },
          {
            "InspectionId": "edd65c1e-a388-4803-9123-10aa06a70b08",
            "RequestedDate": "2025-06-06T16:32:41Z",
            "InspectionType": "P&I - Insulation",
            "InspectionNumber": "792021-2025",
            "InspectionStatus": "Passed",
            "PrimaryInspector": "McLaughlin Matthew",
            "WorkflowActionId": null,
            "ScheduledStartDate": "2025-06-06T04:00:00Z",
            "PrimaryInspectorEmail": "Matthew.McLaughlin@wake.gov",
            "InspectionTypeDescription": "Insulation",
            "IsReinspectionDisplayText": "No"
          },
          {
            "InspectionId": "61ac097e-c7d9-485b-8659-dbc0aaeedd30",
            "RequestedDate": "2025-06-04T15:15:35Z",
            "InspectionType": "P&I - Insulation",
            "InspectionNumber": "790727-2025",
            "InspectionStatus": "Re-inspection required with fee - Permit",
            "PrimaryInspector": "McLaughlin Matthew",
            "WorkflowActionId": null,
            "ScheduledStartDate": "2025-06-04T04:00:00Z",
            "PrimaryInspectorEmail": "Matthew.McLaughlin@wake.gov",
            "InspectionTypeDescription": "Insulation",
            "IsReinspectionDisplayText": "No"
          },
          {
            "InspectionId": "9e02a27d-3655-4d3f-b99b-3c57e06beb24",
            "RequestedDate": "2025-07-11T18:13:02Z",
            "InspectionType": "P&I - Mechanical Final",
            "InspectionNumber": "805250-2025",
            "InspectionStatus": "Passed",
            "PrimaryInspector": "Privette Emerson",
            "WorkflowActionId": null,
            "ScheduledStartDate": "2025-07-11T04:00:00Z",
            "PrimaryInspectorEmail": "emerson.privette@wake.gov",
            "InspectionTypeDescription": "Mechanical Final",
            "IsReinspectionDisplayText": "No"
          },
          {
            "InspectionId": "eb748bca-47de-4b50-84cf-f2af7582013d",
            "RequestedDate": "2025-05-23T16:24:44Z",
            "InspectionType": "P&I - Mechanical Rough",
            "InspectionNumber": "786676-2025",
            "InspectionStatus": "Passed",
            "PrimaryInspector": "Privette Emerson",
            "WorkflowActionId": null,
            "ScheduledStartDate": "2025-05-23T04:00:00Z",
            "PrimaryInspectorEmail": "emerson.privette@wake.gov",
            "InspectionTypeDescription": "Mechanical Rough",
            "IsReinspectionDisplayText": "No"
          },
          {
            "InspectionId": "469ed9da-5d52-47b4-b6d0-9351a08b6361",
            "RequestedDate": "2025-05-22T17:43:18Z",
            "InspectionType": "P&I - Mechanical Rough",
            "InspectionNumber": "786130-2025",
            "InspectionStatus": "Re-inspection required with fee - Permit",
            "PrimaryInspector": "Privette Emerson",
            "WorkflowActionId": null,
            "ScheduledStartDate": "2025-05-22T04:00:00Z",
            "PrimaryInspectorEmail": "emerson.privette@wake.gov",
            "InspectionTypeDescription": "Mechanical Rough",
            "IsReinspectionDisplayText": "No"
          },
          {
            "InspectionId": "9b3081d6-fd92-4686-837d-063dfc2fdc34",
            "RequestedDate": "2025-07-14T14:01:07Z",
            "InspectionType": "P&I - Plumbing Final",
            "InspectionNumber": "806109-2025",
            "InspectionStatus": "Passed",
            "PrimaryInspector": "Privette Emerson",
            "WorkflowActionId": null,
            "ScheduledStartDate": "2025-07-14T04:00:00Z",
            "PrimaryInspectorEmail": "emerson.privette@wake.gov",
            "InspectionTypeDescription": "Plumbing Final",
            "IsReinspectionDisplayText": "No"
          },
          {
            "InspectionId": "138e7545-a62c-42c7-b80c-c1de5d8b3f0a",
            "RequestedDate": "2025-06-20T17:01:54Z",
            "InspectionType": "P&I - Plumbing Groundwork",
            "InspectionNumber": "797249-2025",
            "InspectionStatus": "Passed",
            "PrimaryInspector": "Ielfield Raymond",
            "WorkflowActionId": null,
            "ScheduledStartDate": "2025-06-20T04:00:00Z",
            "PrimaryInspectorEmail": "raymond.ielfield@wake.gov",
            "InspectionTypeDescription": "Plumbing Groundwork",
            "IsReinspectionDisplayText": "No"
          },
          {
            "InspectionId": "511d104d-4438-491d-a42f-7f8a249d53fc",
            "RequestedDate": "2025-05-21T13:03:02Z",
            "InspectionType": "P&I - Plumbing Rough",
            "InspectionNumber": "785233-2025",
            "InspectionStatus": "Passed",
            "PrimaryInspector": "Privette Emerson",
            "WorkflowActionId": null,
            "ScheduledStartDate": "2025-05-21T04:00:00Z",
            "PrimaryInspectorEmail": "emerson.privette@wake.gov",
            "InspectionTypeDescription": "Plumbing Rough",
            "IsReinspectionDisplayText": "No"
          },
          {
            "InspectionId": "7ee42987-9c5d-492c-8e2d-d1af2ecac79b",
            "RequestedDate": "2025-06-20T13:49:17Z",
            "InspectionType": "P&I - Sewer Connection",
            "InspectionNumber": "797047-2025",
            "InspectionStatus": "Passed",
            "PrimaryInspector": "Ielfield Raymond",
            "WorkflowActionId": null,
            "ScheduledStartDate": "2025-06-20T04:00:00Z",
            "PrimaryInspectorEmail": "raymond.ielfield@wake.gov",
            "InspectionTypeDescription": "Sewer Connection",
            "IsReinspectionDisplayText": "No"
          },
          {
            "InspectionId": "ffd2f658-b971-4402-b09e-5837dcb2fdfb",
            "RequestedDate": "2025-06-20T17:01:51Z",
            "InspectionType": "P&I - Sewer Connection",
            "InspectionNumber": "797248-2025",
            "InspectionStatus": "Passed",
            "PrimaryInspector": "Ielfield Raymond",
            "WorkflowActionId": null,
            "ScheduledStartDate": "2025-06-20T04:00:00Z",
            "PrimaryInspectorEmail": "raymond.ielfield@wake.gov",
            "InspectionTypeDescription": "Sewer Connection",
            "IsReinspectionDisplayText": "No"
          },
          {
            "InspectionId": "3de439bd-665d-4fb4-b7f8-bf784f2cb18a",
            "RequestedDate": "2025-06-20T13:49:14Z",
            "InspectionType": "P&I - Water Connection",
            "InspectionNumber": "797046-2025",
            "InspectionStatus": "Passed",
            "PrimaryInspector": "Ielfield Raymond",
            "WorkflowActionId": null,
            "ScheduledStartDate": "2025-06-20T04:00:00Z",
            "PrimaryInspectorEmail": "raymond.ielfield@wake.gov",
            "InspectionTypeDescription": "Water Connection",
            "IsReinspectionDisplayText": "No"
          }
        ],
        "TotalFound": 18
      }
    },
    "last_updated": "2026-06-07T07:30:39.921791+00:00"
  },
  "contacts": {
    "PageCount": 1,
    "TotalFound": 5,
    "CacheKey": "",
    "Result": [
      {
        "ModuleId": 1,
        "EntityId": "b20efcdf-3359-4e49-afc9-4dfb61a68e49",
        "ContactTypeId": "D6DCD76F-6CCF-45D5-B776-71DBB114B144",
        "ContactTypeName": "Applicant",
        "GlobalEntityName": "DR Horton INC",
        "FirstName": "Tracey",
        "LastName": "Davis",
        "IsBilling": true,
        "IsBillingDisplayText": "Yes",
        "Title": "GC-29676-12/31/26",
        "ContactStatus": "N/A",
        "ContactId": "84930ed7-4ba6-41df-9cdb-7f9b18f28c71",
        "GlobalEntityId": "9a30b4c0-ca00-4770-ba83-444c99d29d5f"
      },
      {
        "ModuleId": 1,
        "EntityId": "b20efcdf-3359-4e49-afc9-4dfb61a68e49",
        "ContactTypeId": "85dabff1-4485-4c0f-b82f-406e3e8dcda9",
        "ContactTypeName": "Electrical Contractor",
        "GlobalEntityName": "Romanoff Electric Residential LLC",
        "FirstName": "Kat",
        "LastName": "Allen",
        "IsBilling": true,
        "IsBillingDisplayText": "Yes",
        "Title": "E-12915- 06/11/26",
        "ContactStatus": "Pending",
        "ContactId": "ae68b41c-1377-4321-9a67-a44738ff6006",
        "GlobalEntityId": "43b90361-3f19-4545-a8c4-e362e7338245"
      },
      {
        "ModuleId": 1,
        "EntityId": "b20efcdf-3359-4e49-afc9-4dfb61a68e49",
        "ContactTypeId": "0A5D5D44-8BBC-4343-BBED-6A58BB673BC2",
        "ContactTypeName": "General Contractor",
        "GlobalEntityName": "DR Horton INC",
        "FirstName": "Tracey",
        "LastName": "Davis",
        "IsBilling": false,
        "IsBillingDisplayText": "No",
        "Title": "GC-29676-12/31/26",
        "ContactStatus": "N/A",
        "ContactId": "042ce8a5-fc92-4325-b7f0-5f9195c221de",
        "GlobalEntityId": "9a30b4c0-ca00-4770-ba83-444c99d29d5f"
      },
      {
        "ModuleId": 1,
        "EntityId": "b20efcdf-3359-4e49-afc9-4dfb61a68e49",
        "ContactTypeId": "4a5df9de-729c-4cf5-8d07-d1c93b575a56",
        "ContactTypeName": "Mechanical Contractor",
        "GlobalEntityName": "Weather Master Heating & Air Conditioning, Inc.",
        "FirstName": "Melinda",
        "LastName": "Burns",
        "IsBilling": true,
        "IsBillingDisplayText": "Yes",
        "Title": "H1,2,3 P1-17326  12-31-26  E-14471",
        "ContactStatus": "N/A",
        "ContactId": "813ddcf6-1f10-4c93-b3be-a6426ef87c67",
        "GlobalEntityId": "49d8fd1e-6417-4b9b-9dd0-17828dd5e236"
      },
      {
        "ModuleId": 1,
        "EntityId": "b20efcdf-3359-4e49-afc9-4dfb61a68e49",
        "ContactTypeId": "ea25739a-ccf7-4689-bc7a-668635466766",
        "ContactTypeName": "Plumbing Contractor",
        "GlobalEntityName": "Weather Master Heating & Air Conditioning, Inc.",
        "FirstName": "Melinda",
        "LastName": "Burns",
        "IsBilling": true,
        "IsBillingDisplayText": "Yes",
        "Title": "H1,2,3 P1-17326  12-31-26  E-14471",
        "ContactStatus": "N/A",
        "ContactId": "2d4f1ece-2276-4ca7-a4f7-7a591890803a",
        "GlobalEntityId": "49d8fd1e-6417-4b9b-9dd0-17828dd5e236"
      }
    ],
    "Success": true,
    "ErrorMessage": "",
    "ValidationErrorMessage": "",
    "ConcurrencyErrorMessage": "",
    "StatusCode": 200,
    "BrokenRules": []
  },
  "fees": {
    "PageCount": 1,
    "TotalFound": 9,
    "CacheKey": "",
    "Result": [
      {
        "FeeName": "Homeowner Recovery Fee",
        "InvoiceNumber": "INV-00192748",
        "Computed": 10,
        "AmountDue": 0,
        "InvoiceId": "97b5a475-d583-4d69-a156-03be3b4508c8",
        "Status": null,
        "StatusName": null,
        "TotalFound": 9
      },
      {
        "FeeName": "Reinspection Fee- Building",
        "InvoiceNumber": "INV-00197174",
        "Computed": 60,
        "AmountDue": 0,
        "InvoiceId": "8650fbf8-2fd0-473c-acbf-996320139559",
        "Status": null,
        "StatusName": null,
        "TotalFound": 9
      },
      {
        "FeeName": "Reinspection Fee- Mechanical",
        "InvoiceNumber": "INV-00196030",
        "Computed": 60,
        "AmountDue": 0,
        "InvoiceId": "92bc4d1c-8317-40a4-85b8-ff54cf07dd3e",
        "Status": null,
        "StatusName": null,
        "TotalFound": 9
      },
      {
        "FeeName": "Residential Permit Fee",
        "InvoiceNumber": "INV-00192748",
        "Computed": 968,
        "AmountDue": 0,
        "InvoiceId": "97b5a475-d583-4d69-a156-03be3b4508c8",
        "Status": null,
        "StatusName": null,
        "TotalFound": 9
      },
      {
        "FeeName": "Rolesville  Zoning Permit/Review",
        "InvoiceNumber": "INV-00192748",
        "Computed": 150,
        "AmountDue": 0,
        "InvoiceId": "97b5a475-d583-4d69-a156-03be3b4508c8",
        "Status": null,
        "StatusName": null,
        "TotalFound": 9
      },
      {
        "FeeName": "Rolesville Infrastructure",
        "InvoiceNumber": "INV-00192748",
        "Computed": 200,
        "AmountDue": 0,
        "InvoiceId": "97b5a475-d583-4d69-a156-03be3b4508c8",
        "Status": null,
        "StatusName": null,
        "TotalFound": 9
      },
      {
        "FeeName": "Rolesville Permit Processing",
        "InvoiceNumber": "INV-00192748",
        "Computed": 100,
        "AmountDue": 0,
        "InvoiceId": "97b5a475-d583-4d69-a156-03be3b4508c8",
        "Status": null,
        "StatusName": null,
        "TotalFound": 9
      },
      {
        "FeeName": "Rolesville Recreation Fee",
        "InvoiceNumber": "INV-00192748",
        "Computed": 3200,
        "AmountDue": 0,
        "InvoiceId": "97b5a475-d583-4d69-a156-03be3b4508c8",
        "Status": null,
        "StatusName": null,
        "TotalFound": 9
      },
      {
        "FeeName": "Rolesville Transportation Fee",
        "InvoiceNumber": "INV-00192748",
        "Computed": 3200,
        "AmountDue": 0,
        "InvoiceId": "97b5a475-d583-4d69-a156-03be3b4508c8",
        "Status": null,
        "StatusName": null,
        "TotalFound": 9
      }
    ],
    "Success": true,
    "ErrorMessage": "",
    "ValidationErrorMessage": "",
    "ConcurrencyErrorMessage": "",
    "StatusCode": 200,
    "BrokenRules": []
  },
  "holds": {
    "PageCount": 1,
    "TotalFound": 2,
    "CacheKey": "",
    "Result": [
      {
        "ModuleId": 1,
        "EntityId": "b20efcdf-3359-4e49-afc9-4dfb61a68e49",
        "EntityHoldId": "46b5e0c6-372d-4a9d-acbf-1f3c808b3e65",
        "Name": "Pre Final Hold",
        "HoldTypeId": 2,
        "HoldType": "Stop Action & Alert",
        "HoldReason": "to prevent a finaled date from being placed on any permits (master or sub) when this type of hold is placed on a record.",
        "CreateDate": "2025-04-09T18:34:37Z",
        "Active": true,
        "HoldStatus": "Active",
        "Comments": "RBPR-144560-2025, CBPR-144566-2025, and RABS-144915-2025 must be closed simultaneously.  \n\nThe CBPR, RBPR, and RABS will remain open until the dwelling is converted back to a residence and the garage is no longer used as a sales office. At that time, all three permits will receive a CO and two (2) COCs to sell the dwelling as a residence. \n\nThis is standard practice in Wake County.",
        "AlertMessage": null,
        "AllowPermitApplicationForContact": null,
        "AllowPlanApplicationForContact": null,
        "AllowInspectionRequestForContact": null,
        "AllowNewBusinessForContact": null,
        "AllowNewProfessionalLicenseForContact": null,
        "IsHoldTypeActive": null,
        "NewPermitHoldCheck": null,
        "NewPlanHoldCheck": null,
        "BusinessNewLicenseHoldCheck": null,
        "EnforceMainParcelOnly": null,
        "PermitInspection": null,
        "PlanInspection": null,
        "BusinessInspection": null
      },
      {
        "ModuleId": 1,
        "EntityId": "b20efcdf-3359-4e49-afc9-4dfb61a68e49",
        "EntityHoldId": "6d2243a5-80b8-4c03-8796-c4ab4160d6c1",
        "Name": "Pre Issuance Hold",
        "HoldTypeId": 2,
        "HoldType": "Stop Action & Alert",
        "HoldReason": "to prevent an issue date from being placed on any permits (master or sub) when this type of hold is placed on a record.",
        "CreateDate": "2025-04-09T18:30:37Z",
        "Active": false,
        "HoldStatus": "Inactive",
        "Comments": "Entered in error.",
        "AlertMessage": null,
        "AllowPermitApplicationForContact": null,
        "AllowPlanApplicationForContact": null,
        "AllowInspectionRequestForContact": null,
        "AllowNewBusinessForContact": null,
        "AllowNewProfessionalLicenseForContact": null,
        "IsHoldTypeActive": null,
        "NewPermitHoldCheck": null,
        "NewPlanHoldCheck": null,
        "BusinessNewLicenseHoldCheck": null,
        "EnforceMainParcelOnly": null,
        "PermitInspection": null,
        "PlanInspection": null,
        "BusinessInspection": null
      }
    ],
    "Success": true,
    "ErrorMessage": "",
    "ValidationErrorMessage": "",
    "ConcurrencyErrorMessage": "",
    "StatusCode": 200,
    "BrokenRules": []
  },
  "inspections": {
    "PageCount": 1,
    "TotalFound": 18,
    "CacheKey": "",
    "Result": [
      {
        "ModuleId": 1,
        "EntityId": "b20efcdf-3359-4e49-afc9-4dfb61a68e49",
        "EntityNumber": "",
        "EntityType": "",
        "EntityTypeId": "",
        "EntityClass": "",
        "EntityClassId": "",
        "Address": "",
        "InspectionId": "f26ba1d9-34d5-4e78-be61-d50cec6d8cca",
        "InspectionType": "P&I - Building Final",
        "InspectionTypeId": "4150dd67-aef9-4dea-85e4-0a05feddb6db",
        "InspectionTypeDescription": "Building Final",
        "InspectionStatus": "Passed",
        "ParentInspectionStatus": "",
        "RequestedDate": "2025-08-29T15:44:00Z",
        "ScheduledStartDate": "2025-08-29T04:00:00Z",
        "PrimaryInspector": "Alvarez Alex",
        "PrimaryInspectorEmail": "alejandro.alvarez@wake.gov",
        "IsReinspectionDisplayText": "No",
        "CanCancelInspection": false,
        "CanRequestInspection": true,
        "WorkflowStepId": "",
        "ActionId": "",
        "WorkflowActionId": "",
        "RequestInspectionErrorMessage": null,
        "IsLoggedIn": false,
        "Checked": false,
        "InspectionNumber": "824544-2025",
        "ParentInspectionNumber": "",
        "Reinspection": null,
        "LinkType": null,
        "IsCAPOptionalInspection": false,
        "CaseTypeIds": null,
        "RequestedAMOrPM": 0,
        "ActualDate": null,
        "IsAllowRequestInspectionByPriority": false,
        "ShowRescheduleButton": false,
        "CustomFieldLayoutId": "",
        "OnlineCustomFieldLayoutId": "",
        "CustomFields": null,
        "CustomFieldLayout": null,
        "CustomLayout": null,
        "IsCompletedFlag": false,
        "IsFailureFlag": false,
        "IsCancelledFlag": false,
        "IsSuccessFlag": false,
        "LicenseSystemStatusName": "",
        "LicenseSystemStatusId": 0,
        "IsPreventRequestInspection": false,
        "Contacts": null,
        "StatusName": null
      },
      {
        "ModuleId": 1,
        "EntityId": "b20efcdf-3359-4e49-afc9-4dfb61a68e49",
        "EntityNumber": "",
        "EntityType": "",
        "EntityTypeId": "",
        "EntityClass": "",
        "EntityClassId": "",
        "Address": "",
        "InspectionId": "c84ee197-426c-455f-8039-acd67fa14f2c",
        "InspectionType": "P&I - Electrical Final",
        "InspectionTypeId": "b3c0b3a7-856b-4029-ad75-415b37ff280f",
        "InspectionTypeDescription": "Electrical Final",
        "InspectionStatus": "Passed",
        "ParentInspectionStatus": "",
        "RequestedDate": "2025-07-11T16:37:43Z",
        "ScheduledStartDate": "2025-07-11T04:00:00Z",
        "PrimaryInspector": "Privette Emerson",
        "PrimaryInspectorEmail": "emerson.privette@wake.gov",
        "IsReinspectionDisplayText": "No",
        "CanCancelInspection": false,
        "CanRequestInspection": true,
        "WorkflowStepId": "",
        "ActionId": "",
        "WorkflowActionId": "",
        "RequestInspectionErrorMessage": null,
        "IsLoggedIn": false,
        "Checked": false,
        "InspectionNumber": "805091-2025",
        "ParentInspectionNumber": "",
        "Reinspection": null,
        "LinkType": null,
        "IsCAPOptionalInspection": false,
        "CaseTypeIds": null,
        "RequestedAMOrPM": 0,
        "ActualDate": null,
        "IsAllowRequestInspectionByPriority": false,
        "ShowRescheduleButton": false,
        "CustomFieldLayoutId": "",
        "OnlineCustomFieldLayoutId": "",
        "CustomFields": null,
        "CustomFieldLayout": null,
        "CustomLayout": null,
        "IsCompletedFlag": false,
        "IsFailureFlag": false,
        "IsCancelledFlag": false,
        "IsSuccessFlag": false,
        "LicenseSystemStatusName": "",
        "LicenseSystemStatusId": 0,
        "IsPreventRequestInspection": false,
        "Contacts": null,
        "StatusName": null
      },
      {
        "ModuleId": 1,
        "EntityId": "b20efcdf-3359-4e49-afc9-4dfb61a68e49",
        "EntityNumber": "",
        "EntityType": "",
        "EntityTypeId": "",
        "EntityClass": "",
        "EntityClassId": "",
        "Address": "",
        "InspectionId": "3a991cb2-aa99-43ac-a709-7f9499dbb081",
        "InspectionType": "P&I - Electrical Rough",
        "InspectionTypeId": "240cc60d-5269-4248-b4e8-2fd72859bfe0",
        "InspectionTypeDescription": "Electrical Rough",
        "InspectionStatus": "Passed",
        "ParentInspectionStatus": "",
        "RequestedDate": "2025-05-27T15:50:10Z",
        "ScheduledStartDate": "2025-05-27T04:00:00Z",
        "PrimaryInspector": "Piratzky Andy",
        "PrimaryInspectorEmail": "andy.piratzky@wake.gov",
        "IsReinspectionDisplayText": "No",
        "CanCancelInspection": false,
        "CanRequestInspection": true,
        "WorkflowStepId": "",
        "ActionId": "",
        "WorkflowActionId": "",
        "RequestInspectionErrorMessage": null,
        "IsLoggedIn": false,
        "Checked": false,
        "InspectionNumber": "787194-2025",
        "ParentInspectionNumber": "",
        "Reinspection": null,
        "LinkType": null,
        "IsCAPOptionalInspection": false,
        "CaseTypeIds": null,
        "RequestedAMOrPM": 0,
        "ActualDate": null,
        "IsAllowRequestInspectionByPriority": false,
        "ShowRescheduleButton": false,
        "CustomFieldLayoutId": "",
        "OnlineCustomFieldLayoutId": "",
        "CustomFields": null,
        "CustomFieldLayout": null,
        "CustomLayout": null,
        "IsCompletedFlag": false,
        "IsFailureFlag": false,
        "IsCancelledFlag": false,
        "IsSuccessFlag": false,
        "LicenseSystemStatusName": "",
        "LicenseSystemStatusId": 0,
        "IsPreventRequestInspection": false,
        "Contacts": null,
        "StatusName": null
      },
      {
        "ModuleId": 1,
        "EntityId": "b20efcdf-3359-4e49-afc9-4dfb61a68e49",
        "EntityNumber": "",
        "EntityType": "",
        "EntityTypeId": "",
        "EntityClass": "",
        "EntityClassId": "",
        "Address": "",
        "InspectionId": "4a7ff7c4-1bfc-4f41-be67-3341e53f2ec9",
        "InspectionType": "P&I - Floor Framing",
        "InspectionTypeId": "6ccc6bc8-2545-4872-b781-fa757faf2790",
        "InspectionTypeDescription": "Floor Framing",
        "InspectionStatus": "Passed",
        "ParentInspectionStatus": "",
        "RequestedDate": "2025-05-08T04:00:00Z",
        "ScheduledStartDate": "2025-05-08T13:00:00Z",
        "PrimaryInspector": "McLaughlin Matthew",
        "PrimaryInspectorEmail": "Matthew.McLaughlin@wake.gov",
        "IsReinspectionDisplayText": "No",
        "CanCancelInspection": false,
        "CanRequestInspection": true,
        "WorkflowStepId": "",
        "ActionId": "",
        "WorkflowActionId": "",
        "RequestInspectionErrorMessage": null,
        "IsLoggedIn": false,
        "Checked": false,
        "InspectionNumber": "780794-2025",
        "ParentInspectionNumber": "",
        "Reinspection": null,
        "LinkType": null,
        "IsCAPOptionalInspection": false,
        "CaseTypeIds": null,
        "RequestedAMOrPM": 0,
        "ActualDate": null,
        "IsAllowRequestInspectionByPriority": false,
        "ShowRescheduleButton": false,
        "CustomFieldLayoutId": "",
        "OnlineCustomFieldLayoutId": "",
        "CustomFields": null,
        "CustomFieldLayout": null,
        "CustomLayout": null,
        "IsCompletedFlag": false,
        "IsFailureFlag": false,
        "IsCancelledFlag": false,
        "IsSuccessFlag": false,
        "LicenseSystemStatusName": "",
        "LicenseSystemStatusId": 0,
        "IsPreventRequestInspection": false,
        "Contacts": null,
        "StatusName": null
      },
      {
        "ModuleId": 1,
        "EntityId": "b20efcdf-3359-4e49-afc9-4dfb61a68e49",
        "EntityNumber": "",
        "EntityType": "",
        "EntityTypeId": "",
        "EntityClass": "",
        "EntityClassId": "",
        "Address": "",
        "InspectionId": "48ec3839-2288-4252-9650-c7ec838e988d",
        "InspectionType": "P&I - Footing or Monolithic Slab",
        "InspectionTypeId": "5a9c8171-ebc5-4d0d-b78b-7ad764700b36",
        "InspectionTypeDescription": "Footing or Monolithic Slab",
        "InspectionStatus": "Passed",
        "ParentInspectionStatus": "",
        "RequestedDate": "2025-05-07T16:08:06Z",
        "ScheduledStartDate": "2025-05-07T04:00:00Z",
        "PrimaryInspector": "Alvarez Alex",
        "PrimaryInspectorEmail": "alejandro.alvarez@wake.gov",
        "IsReinspectionDisplayText": "No",
        "CanCancelInspection": false,
        "CanRequestInspection": true,
        "WorkflowStepId": "",
        "ActionId": "",
        "WorkflowActionId": "",
        "RequestInspectionErrorMessage": null,
        "IsLoggedIn": false,
        "Checked": false,
        "InspectionNumber": "779839-2025",
        "ParentInspectionNumber": "",
        "Reinspection": null,
        "LinkType": null,
        "IsCAPOptionalInspection": false,
        "CaseTypeIds": null,
        "RequestedAMOrPM": 0,
        "ActualDate": null,
        "IsAllowRequestInspectionByPriority": false,
        "ShowRescheduleButton": false,
        "CustomFieldLayoutId": "",
        "OnlineCustomFieldLayoutId": "",
        "CustomFields": null,
        "CustomFieldLayout": null,
        "CustomLayout": null,
        "IsCompletedFlag": false,
        "IsFailureFlag": false,
        "IsCancelledFlag": false,
        "IsSuccessFlag": false,
        "LicenseSystemStatusName": "",
        "LicenseSystemStatusId": 0,
        "IsPreventRequestInspection": false,
        "Contacts": null,
        "StatusName": null
      },
      {
        "ModuleId": 1,
        "EntityId": "b20efcdf-3359-4e49-afc9-4dfb61a68e49",
        "EntityNumber": "",
        "EntityType": "",
        "EntityTypeId": "",
        "EntityClass": "",
        "EntityClassId": "",
        "Address": "",
        "InspectionId": "ed9adc72-d14e-4373-9a2a-11a2ae971aad",
        "InspectionType": "P&I - Foundation",
        "InspectionTypeId": "e9245c97-8bcf-4471-ac70-c48d7710346b",
        "InspectionTypeDescription": "Foundation",
        "InspectionStatus": "Passed",
        "ParentInspectionStatus": "",
        "RequestedDate": "2025-05-08T16:02:35Z",
        "ScheduledStartDate": "2025-05-08T04:00:00Z",
        "PrimaryInspector": "McLaughlin Matthew",
        "PrimaryInspectorEmail": "Matthew.McLaughlin@wake.gov",
        "IsReinspectionDisplayText": "No",
        "CanCancelInspection": false,
        "CanRequestInspection": true,
        "WorkflowStepId": "",
        "ActionId": "",
        "WorkflowActionId": "",
        "RequestInspectionErrorMessage": null,
        "IsLoggedIn": false,
        "Checked": false,
        "InspectionNumber": "780376-2025",
        "ParentInspectionNumber": "",
        "Reinspection": null,
        "LinkType": null,
        "IsCAPOptionalInspection": false,
        "CaseTypeIds": null,
        "RequestedAMOrPM": 0,
        "ActualDate": null,
        "IsAllowRequestInspectionByPriority": false,
        "ShowRescheduleButton": false,
        "CustomFieldLayoutId": "",
        "OnlineCustomFieldLayoutId": "",
        "CustomFields": null,
        "CustomFieldLayout": null,
        "CustomLayout": null,
        "IsCompletedFlag": false,
        "IsFailureFlag": false,
        "IsCancelledFlag": false,
        "IsSuccessFlag": false,
        "LicenseSystemStatusName": "",
        "LicenseSystemStatusId": 0,
        "IsPreventRequestInspection": false,
        "Contacts": null,
        "StatusName": null
      },
      {
        "ModuleId": 1,
        "EntityId": "b20efcdf-3359-4e49-afc9-4dfb61a68e49",
        "EntityNumber": "",
        "EntityType": "",
        "EntityTypeId": "",
        "EntityClass": "",
        "EntityClassId": "",
        "Address": "",
        "InspectionId": "48db665f-57da-4b8d-a22a-0642e9450b79",
        "InspectionType": "P&I - Framing",
        "InspectionTypeId": "cec7b24f-2730-459e-a19b-af0a4d7d1903",
        "InspectionTypeDescription": "Framing",
        "InspectionStatus": "Passed with Conditions",
        "ParentInspectionStatus": "",
        "RequestedDate": "2025-05-28T15:47:18Z",
        "ScheduledStartDate": "2025-05-28T04:00:00Z",
        "PrimaryInspector": "McLaughlin Matthew",
        "PrimaryInspectorEmail": "Matthew.McLaughlin@wake.gov",
        "IsReinspectionDisplayText": "No",
        "CanCancelInspection": false,
        "CanRequestInspection": true,
        "WorkflowStepId": "",
        "ActionId": "",
        "WorkflowActionId": "",
        "RequestInspectionErrorMessage": null,
        "IsLoggedIn": false,
        "Checked": false,
        "InspectionNumber": "787767-2025",
        "ParentInspectionNumber": "",
        "Reinspection": null,
        "LinkType": null,
        "IsCAPOptionalInspection": false,
        "CaseTypeIds": null,
        "RequestedAMOrPM": 0,
        "ActualDate": null,
        "IsAllowRequestInspectionByPriority": false,
        "ShowRescheduleButton": false,
        "CustomFieldLayoutId": "",
        "OnlineCustomFieldLayoutId": "",
        "CustomFields": null,
        "CustomFieldLayout": null,
        "CustomLayout": null,
        "IsCompletedFlag": false,
        "IsFailureFlag": false,
        "IsCancelledFlag": false,
        "IsSuccessFlag": false,
        "LicenseSystemStatusName": "",
        "LicenseSystemStatusId": 0,
        "IsPreventRequestInspection": false,
        "Contacts": null,
        "StatusName": null
      },
      {
        "ModuleId": 1,
        "EntityId": "b20efcdf-3359-4e49-afc9-4dfb61a68e49",
        "EntityNumber": "",
        "EntityType": "",
        "EntityTypeId": "",
        "EntityClass": "",
        "EntityClassId": "",
        "Address": "",
        "InspectionId": "edd65c1e-a388-4803-9123-10aa06a70b08",
        "InspectionType": "P&I - Insulation",
        "InspectionTypeId": "55ba7552-75d0-49b7-931f-998f1b267782",
        "InspectionTypeDescription": "Insulation",
        "InspectionStatus": "Passed",
        "ParentInspectionStatus": "",
        "RequestedDate": "2025-06-06T16:32:41Z",
        "ScheduledStartDate": "2025-06-06T04:00:00Z",
        "PrimaryInspector": "McLaughlin Matthew",
        "PrimaryInspectorEmail": "Matthew.McLaughlin@wake.gov",
        "IsReinspectionDisplayText": "No",
        "CanCancelInspection": false,
        "CanRequestInspection": true,
        "WorkflowStepId": "",
        "ActionId": "",
        "WorkflowActionId": "",
        "RequestInspectionErrorMessage": null,
        "IsLoggedIn": false,
        "Checked": false,
        "InspectionNumber": "792021-2025",
        "ParentInspectionNumber": "",
        "Reinspection": null,
        "LinkType": null,
        "IsCAPOptionalInspection": false,
        "CaseTypeIds": null,
        "RequestedAMOrPM": 0,
        "ActualDate": null,
        "IsAllowRequestInspectionByPriority": false,
        "ShowRescheduleButton": false,
        "CustomFieldLayoutId": "",
        "OnlineCustomFieldLayoutId": "",
        "CustomFields": null,
        "CustomFieldLayout": null,
        "CustomLayout": null,
        "IsCompletedFlag": false,
        "IsFailureFlag": false,
        "IsCancelledFlag": false,
        "IsSuccessFlag": false,
        "LicenseSystemStatusName": "",
        "LicenseSystemStatusId": 0,
        "IsPreventRequestInspection": false,
        "Contacts": null,
        "StatusName": null
      },
      {
        "ModuleId": 1,
        "EntityId": "b20efcdf-3359-4e49-afc9-4dfb61a68e49",
        "EntityNumber": "",
        "EntityType": "",
        "EntityTypeId": "",
        "EntityClass": "",
        "EntityClassId": "",
        "Address": "",
        "InspectionId": "61ac097e-c7d9-485b-8659-dbc0aaeedd30",
        "InspectionType": "P&I - Insulation",
        "InspectionTypeId": "55ba7552-75d0-49b7-931f-998f1b267782",
        "InspectionTypeDescription": "Insulation",
        "InspectionStatus": "Re-inspection required with fee - Permit",
        "ParentInspectionStatus": "",
        "RequestedDate": "2025-06-04T15:15:35Z",
        "ScheduledStartDate": "2025-06-04T04:00:00Z",
        "PrimaryInspector": "McLaughlin Matthew",
        "PrimaryInspectorEmail": "Matthew.McLaughlin@wake.gov",
        "IsReinspectionDisplayText": "No",
        "CanCancelInspection": false,
        "CanRequestInspection": true,
        "WorkflowStepId": "",
        "ActionId": "",
        "WorkflowActionId": "",
        "RequestInspectionErrorMessage": null,
        "IsLoggedIn": false,
        "Checked": false,
        "InspectionNumber": "790727-2025",
        "ParentInspectionNumber": "",
        "Reinspection": null,
        "LinkType": null,
        "IsCAPOptionalInspection": false,
        "CaseTypeIds": null,
        "RequestedAMOrPM": 0,
        "ActualDate": null,
        "IsAllowRequestInspectionByPriority": false,
        "ShowRescheduleButton": false,
        "CustomFieldLayoutId": "",
        "OnlineCustomFieldLayoutId": "",
        "CustomFields": null,
        "CustomFieldLayout": null,
        "CustomLayout": null,
        "IsCompletedFlag": false,
        "IsFailureFlag": false,
        "IsCancelledFlag": false,
        "IsSuccessFlag": false,
        "LicenseSystemStatusName": "",
        "LicenseSystemStatusId": 0,
        "IsPreventRequestInspection": false,
        "Contacts": null,
        "StatusName": null
      },
      {
        "ModuleId": 1,
        "EntityId": "b20efcdf-3359-4e49-afc9-4dfb61a68e49",
        "EntityNumber": "",
        "EntityType": "",
        "EntityTypeId": "",
        "EntityClass": "",
        "EntityClassId": "",
        "Address": "",
        "InspectionId": "9e02a27d-3655-4d3f-b99b-3c57e06beb24",
        "InspectionType": "P&I - Mechanical Final",
        "InspectionTypeId": "f952fd3c-b140-4a8c-8790-17c27c33ab83",
        "InspectionTypeDescription": "Mechanical Final",
        "InspectionStatus": "Passed",
        "ParentInspectionStatus": "",
        "RequestedDate": "2025-07-11T18:13:02Z",
        "ScheduledStartDate": "2025-07-11T04:00:00Z",
        "PrimaryInspector": "Privette Emerson",
        "PrimaryInspectorEmail": "emerson.privette@wake.gov",
        "IsReinspectionDisplayText": "No",
        "CanCancelInspection": false,
        "CanRequestInspection": true,
        "WorkflowStepId": "",
        "ActionId": "",
        "WorkflowActionId": "",
        "RequestInspectionErrorMessage": null,
        "IsLoggedIn": false,
        "Checked": false,
        "InspectionNumber": "805250-2025",
        "ParentInspectionNumber": "",
        "Reinspection": null,
        "LinkType": null,
        "IsCAPOptionalInspection": false,
        "CaseTypeIds": null,
        "RequestedAMOrPM": 0,
        "ActualDate": null,
        "IsAllowRequestInspectionByPriority": false,
        "ShowRescheduleButton": false,
        "CustomFieldLayoutId": "",
        "OnlineCustomFieldLayoutId": "",
        "CustomFields": null,
        "CustomFieldLayout": null,
        "CustomLayout": null,
        "IsCompletedFlag": false,
        "IsFailureFlag": false,
        "IsCancelledFlag": false,
        "IsSuccessFlag": false,
        "LicenseSystemStatusName": "",
        "LicenseSystemStatusId": 0,
        "IsPreventRequestInspection": false,
        "Contacts": null,
        "StatusName": null
      },
      {
        "ModuleId": 1,
        "EntityId": "b20efcdf-3359-4e49-afc9-4dfb61a68e49",
        "EntityNumber": "",
        "EntityType": "",
        "EntityTypeId": "",
        "EntityClass": "",
        "EntityClassId": "",
        "Address": "",
        "InspectionId": "eb748bca-47de-4b50-84cf-f2af7582013d",
        "InspectionType": "P&I - Mechanical Rough",
        "InspectionTypeId": "4ca748ab-1157-438a-9e67-8efaea171edf",
        "InspectionTypeDescription": "Mechanical Rough",
        "InspectionStatus": "Passed",
        "ParentInspectionStatus": "",
        "RequestedDate": "2025-05-23T16:24:44Z",
        "ScheduledStartDate": "2025-05-23T04:00:00Z",
        "PrimaryInspector": "Privette Emerson",
        "PrimaryInspectorEmail": "emerson.privette@wake.gov",
        "IsReinspectionDisplayText": "No",
        "CanCancelInspection": false,
        "CanRequestInspection": true,
        "WorkflowStepId": "",
        "ActionId": "",
        "WorkflowActionId": "",
        "RequestInspectionErrorMessage": null,
        "IsLoggedIn": false,
        "Checked": false,
        "InspectionNumber": "786676-2025",
        "ParentInspectionNumber": "",
        "Reinspection": null,
        "LinkType": null,
        "IsCAPOptionalInspection": false,
        "CaseTypeIds": null,
        "RequestedAMOrPM": 0,
        "ActualDate": null,
        "IsAllowRequestInspectionByPriority": false,
        "ShowRescheduleButton": false,
        "CustomFieldLayoutId": "",
        "OnlineCustomFieldLayoutId": "",
        "CustomFields": null,
        "CustomFieldLayout": null,
        "CustomLayout": null,
        "IsCompletedFlag": false,
        "IsFailureFlag": false,
        "IsCancelledFlag": false,
        "IsSuccessFlag": false,
        "LicenseSystemStatusName": "",
        "LicenseSystemStatusId": 0,
        "IsPreventRequestInspection": false,
        "Contacts": null,
        "StatusName": null
      },
      {
        "ModuleId": 1,
        "EntityId": "b20efcdf-3359-4e49-afc9-4dfb61a68e49",
        "EntityNumber": "",
        "EntityType": "",
        "EntityTypeId": "",
        "EntityClass": "",
        "EntityClassId": "",
        "Address": "",
        "InspectionId": "469ed9da-5d52-47b4-b6d0-9351a08b6361",
        "InspectionType": "P&I - Mechanical Rough",
        "InspectionTypeId": "4ca748ab-1157-438a-9e67-8efaea171edf",
        "InspectionTypeDescription": "Mechanical Rough",
        "InspectionStatus": "Re-inspection required with fee - Permit",
        "ParentInspectionStatus": "",
        "RequestedDate": "2025-05-22T17:43:18Z",
        "ScheduledStartDate": "2025-05-22T04:00:00Z",
        "PrimaryInspector": "Privette Emerson",
        "PrimaryInspectorEmail": "emerson.privette@wake.gov",
        "IsReinspectionDisplayText": "No",
        "CanCancelInspection": false,
        "CanRequestInspection": true,
        "WorkflowStepId": "",
        "ActionId": "",
        "WorkflowActionId": "",
        "RequestInspectionErrorMessage": null,
        "IsLoggedIn": false,
        "Checked": false,
        "InspectionNumber": "786130-2025",
        "ParentInspectionNumber": "",
        "Reinspection": null,
        "LinkType": null,
        "IsCAPOptionalInspection": false,
        "CaseTypeIds": null,
        "RequestedAMOrPM": 0,
        "ActualDate": null,
        "IsAllowRequestInspectionByPriority": false,
        "ShowRescheduleButton": false,
        "CustomFieldLayoutId": "",
        "OnlineCustomFieldLayoutId": "",
        "CustomFields": null,
        "CustomFieldLayout": null,
        "CustomLayout": null,
        "IsCompletedFlag": false,
        "IsFailureFlag": false,
        "IsCancelledFlag": false,
        "IsSuccessFlag": false,
        "LicenseSystemStatusName": "",
        "LicenseSystemStatusId": 0,
        "IsPreventRequestInspection": false,
        "Contacts": null,
        "StatusName": null
      },
      {
        "ModuleId": 1,
        "EntityId": "b20efcdf-3359-4e49-afc9-4dfb61a68e49",
        "EntityNumber": "",
        "EntityType": "",
        "EntityTypeId": "",
        "EntityClass": "",
        "EntityClassId": "",
        "Address": "",
        "InspectionId": "9b3081d6-fd92-4686-837d-063dfc2fdc34",
        "InspectionType": "P&I - Plumbing Final",
        "InspectionTypeId": "4f1ca963-7439-4fc6-a13b-68bae8a4026a",
        "InspectionTypeDescription": "Plumbing Final",
        "InspectionStatus": "Passed",
        "ParentInspectionStatus": "",
        "RequestedDate": "2025-07-14T14:01:07Z",
        "ScheduledStartDate": "2025-07-14T04:00:00Z",
        "PrimaryInspector": "Privette Emerson",
        "PrimaryInspectorEmail": "emerson.privette@wake.gov",
        "IsReinspectionDisplayText": "No",
        "CanCancelInspection": false,
        "CanRequestInspection": true,
        "WorkflowStepId": "",
        "ActionId": "",
        "WorkflowActionId": "",
        "RequestInspectionErrorMessage": null,
        "IsLoggedIn": false,
        "Checked": false,
        "InspectionNumber": "806109-2025",
        "ParentInspectionNumber": "",
        "Reinspection": null,
        "LinkType": null,
        "IsCAPOptionalInspection": false,
        "CaseTypeIds": null,
        "RequestedAMOrPM": 0,
        "ActualDate": null,
        "IsAllowRequestInspectionByPriority": false,
        "ShowRescheduleButton": false,
        "CustomFieldLayoutId": "",
        "OnlineCustomFieldLayoutId": "",
        "CustomFields": null,
        "CustomFieldLayout": null,
        "CustomLayout": null,
        "IsCompletedFlag": false,
        "IsFailureFlag": false,
        "IsCancelledFlag": false,
        "IsSuccessFlag": false,
        "LicenseSystemStatusName": "",
        "LicenseSystemStatusId": 0,
        "IsPreventRequestInspection": false,
        "Contacts": null,
        "StatusName": null
      },
      {
        "ModuleId": 1,
        "EntityId": "b20efcdf-3359-4e49-afc9-4dfb61a68e49",
        "EntityNumber": "",
        "EntityType": "",
        "EntityTypeId": "",
        "EntityClass": "",
        "EntityClassId": "",
        "Address": "",
        "InspectionId": "138e7545-a62c-42c7-b80c-c1de5d8b3f0a",
        "InspectionType": "P&I - Plumbing Groundwork",
        "InspectionTypeId": "cfdfcbd7-9758-4a0b-ba00-f93a00e6dd31",
        "InspectionTypeDescription": "Plumbing Groundwork",
        "InspectionStatus": "Passed",
        "ParentInspectionStatus": "",
        "RequestedDate": "2025-06-20T17:01:54Z",
        "ScheduledStartDate": "2025-06-20T04:00:00Z",
        "PrimaryInspector": "Ielfield Raymond",
        "PrimaryInspectorEmail": "raymond.ielfield@wake.gov",
        "IsReinspectionDisplayText": "No",
        "CanCancelInspection": false,
        "CanRequestInspection": true,
        "WorkflowStepId": "",
        "ActionId": "",
        "WorkflowActionId": "",
        "RequestInspectionErrorMessage": null,
        "IsLoggedIn": false,
        "Checked": false,
        "InspectionNumber": "797249-2025",
        "ParentInspectionNumber": "",
        "Reinspection": null,
        "LinkType": null,
        "IsCAPOptionalInspection": false,
        "CaseTypeIds": null,
        "RequestedAMOrPM": 0,
        "ActualDate": null,
        "IsAllowRequestInspectionByPriority": false,
        "ShowRescheduleButton": false,
        "CustomFieldLayoutId": "",
        "OnlineCustomFieldLayoutId": "",
        "CustomFields": null,
        "CustomFieldLayout": null,
        "CustomLayout": null,
        "IsCompletedFlag": false,
        "IsFailureFlag": false,
        "IsCancelledFlag": false,
        "IsSuccessFlag": false,
        "LicenseSystemStatusName": "",
        "LicenseSystemStatusId": 0,
        "IsPreventRequestInspection": false,
        "Contacts": null,
        "StatusName": null
      },
      {
        "ModuleId": 1,
        "EntityId": "b20efcdf-3359-4e49-afc9-4dfb61a68e49",
        "EntityNumber": "",
        "EntityType": "",
        "EntityTypeId": "",
        "EntityClass": "",
        "EntityClassId": "",
        "Address": "",
        "InspectionId": "511d104d-4438-491d-a42f-7f8a249d53fc",
        "InspectionType": "P&I - Plumbing Rough",
        "InspectionTypeId": "cc812db9-e53a-4201-813c-b3521b345d2a",
        "InspectionTypeDescription": "Plumbing Rough",
        "InspectionStatus": "Passed",
        "ParentInspectionStatus": "",
        "RequestedDate": "2025-05-21T13:03:02Z",
        "ScheduledStartDate": "2025-05-21T04:00:00Z",
        "PrimaryInspector": "Privette Emerson",
        "PrimaryInspectorEmail": "emerson.privette@wake.gov",
        "IsReinspectionDisplayText": "No",
        "CanCancelInspection": false,
        "CanRequestInspection": true,
        "WorkflowStepId": "",
        "ActionId": "",
        "WorkflowActionId": "",
        "RequestInspectionErrorMessage": null,
        "IsLoggedIn": false,
        "Checked": false,
        "InspectionNumber": "785233-2025",
        "ParentInspectionNumber": "",
        "Reinspection": null,
        "LinkType": null,
        "IsCAPOptionalInspection": false,
        "CaseTypeIds": null,
        "RequestedAMOrPM": 0,
        "ActualDate": null,
        "IsAllowRequestInspectionByPriority": false,
        "ShowRescheduleButton": false,
        "CustomFieldLayoutId": "",
        "OnlineCustomFieldLayoutId": "",
        "CustomFields": null,
        "CustomFieldLayout": null,
        "CustomLayout": null,
        "IsCompletedFlag": false,
        "IsFailureFlag": false,
        "IsCancelledFlag": false,
        "IsSuccessFlag": false,
        "LicenseSystemStatusName": "",
        "LicenseSystemStatusId": 0,
        "IsPreventRequestInspection": false,
        "Contacts": null,
        "StatusName": null
      },
      {
        "ModuleId": 1,
        "EntityId": "b20efcdf-3359-4e49-afc9-4dfb61a68e49",
        "EntityNumber": "",
        "EntityType": "",
        "EntityTypeId": "",
        "EntityClass": "",
        "EntityClassId": "",
        "Address": "",
        "InspectionId": "7ee42987-9c5d-492c-8e2d-d1af2ecac79b",
        "InspectionType": "P&I - Sewer Connection",
        "InspectionTypeId": "41432d1f-6888-4ba0-8be6-dd76aeffe186",
        "InspectionTypeDescription": "Sewer Connection",
        "InspectionStatus": "Passed",
        "ParentInspectionStatus": "",
        "RequestedDate": "2025-06-20T13:49:17Z",
        "ScheduledStartDate": "2025-06-20T04:00:00Z",
        "PrimaryInspector": "Ielfield Raymond",
        "PrimaryInspectorEmail": "raymond.ielfield@wake.gov",
        "IsReinspectionDisplayText": "No",
        "CanCancelInspection": false,
        "CanRequestInspection": true,
        "WorkflowStepId": "",
        "ActionId": "",
        "WorkflowActionId": "",
        "RequestInspectionErrorMessage": null,
        "IsLoggedIn": false,
        "Checked": false,
        "InspectionNumber": "797047-2025",
        "ParentInspectionNumber": "",
        "Reinspection": null,
        "LinkType": null,
        "IsCAPOptionalInspection": false,
        "CaseTypeIds": null,
        "RequestedAMOrPM": 0,
        "ActualDate": null,
        "IsAllowRequestInspectionByPriority": false,
        "ShowRescheduleButton": false,
        "CustomFieldLayoutId": "",
        "OnlineCustomFieldLayoutId": "",
        "CustomFields": null,
        "CustomFieldLayout": null,
        "CustomLayout": null,
        "IsCompletedFlag": false,
        "IsFailureFlag": false,
        "IsCancelledFlag": false,
        "IsSuccessFlag": false,
        "LicenseSystemStatusName": "",
        "LicenseSystemStatusId": 0,
        "IsPreventRequestInspection": false,
        "Contacts": null,
        "StatusName": null
      },
      {
        "ModuleId": 1,
        "EntityId": "b20efcdf-3359-4e49-afc9-4dfb61a68e49",
        "EntityNumber": "",
        "EntityType": "",
        "EntityTypeId": "",
        "EntityClass": "",
        "EntityClassId": "",
        "Address": "",
        "InspectionId": "ffd2f658-b971-4402-b09e-5837dcb2fdfb",
        "InspectionType": "P&I - Sewer Connection",
        "InspectionTypeId": "41432d1f-6888-4ba0-8be6-dd76aeffe186",
        "InspectionTypeDescription": "Sewer Connection",
        "InspectionStatus": "Passed",
        "ParentInspectionStatus": "",
        "RequestedDate": "2025-06-20T17:01:51Z",
        "ScheduledStartDate": "2025-06-20T04:00:00Z",
        "PrimaryInspector": "Ielfield Raymond",
        "PrimaryInspectorEmail": "raymond.ielfield@wake.gov",
        "IsReinspectionDisplayText": "No",
        "CanCancelInspection": false,
        "CanRequestInspection": true,
        "WorkflowStepId": "",
        "ActionId": "",
        "WorkflowActionId": "",
        "RequestInspectionErrorMessage": null,
        "IsLoggedIn": false,
        "Checked": false,
        "InspectionNumber": "797248-2025",
        "ParentInspectionNumber": "",
        "Reinspection": null,
        "LinkType": null,
        "IsCAPOptionalInspection": false,
        "CaseTypeIds": null,
        "RequestedAMOrPM": 0,
        "ActualDate": null,
        "IsAllowRequestInspectionByPriority": false,
        "ShowRescheduleButton": false,
        "CustomFieldLayoutId": "",
        "OnlineCustomFieldLayoutId": "",
        "CustomFields": null,
        "CustomFieldLayout": null,
        "CustomLayout": null,
        "IsCompletedFlag": false,
        "IsFailureFlag": false,
        "IsCancelledFlag": false,
        "IsSuccessFlag": false,
        "LicenseSystemStatusName": "",
        "LicenseSystemStatusId": 0,
        "IsPreventRequestInspection": false,
        "Contacts": null,
        "StatusName": null
      },
      {
        "ModuleId": 1,
        "EntityId": "b20efcdf-3359-4e49-afc9-4dfb61a68e49",
        "EntityNumber": "",
        "EntityType": "",
        "EntityTypeId": "",
        "EntityClass": "",
        "EntityClassId": "",
        "Address": "",
        "InspectionId": "3de439bd-665d-4fb4-b7f8-bf784f2cb18a",
        "InspectionType": "P&I - Water Connection",
        "InspectionTypeId": "87e0fa82-1261-42de-9d2a-1f390fe5861a",
        "InspectionTypeDescription": "Water Connection",
        "InspectionStatus": "Passed",
        "ParentInspectionStatus": "",
        "RequestedDate": "2025-06-20T13:49:14Z",
        "ScheduledStartDate": "2025-06-20T04:00:00Z",
        "PrimaryInspector": "Ielfield Raymond",
        "PrimaryInspectorEmail": "raymond.ielfield@wake.gov",
        "IsReinspectionDisplayText": "No",
        "CanCancelInspection": false,
        "CanRequestInspection": true,
        "WorkflowStepId": "",
        "ActionId": "",
        "WorkflowActionId": "",
        "RequestInspectionErrorMessage": null,
        "IsLoggedIn": false,
        "Checked": false,
        "InspectionNumber": "797046-2025",
        "ParentInspectionNumber": "",
        "Reinspection": null,
        "LinkType": null,
        "IsCAPOptionalInspection": false,
        "CaseTypeIds": null,
        "RequestedAMOrPM": 0,
        "ActualDate": null,
        "IsAllowRequestInspectionByPriority": false,
        "ShowRescheduleButton": false,
        "CustomFieldLayoutId": "",
        "OnlineCustomFieldLayoutId": "",
        "CustomFields": null,
        "CustomFieldLayout": null,
        "CustomLayout": null,
        "IsCompletedFlag": false,
        "IsFailureFlag": false,
        "IsCancelledFlag": false,
        "IsSuccessFlag": false,
        "LicenseSystemStatusName": "",
        "LicenseSystemStatusId": 0,
        "IsPreventRequestInspection": false,
        "Contacts": null,
        "StatusName": null
      }
    ],
    "Success": true,
    "ErrorMessage": "",
    "ValidationErrorMessage": "",
    "ConcurrencyErrorMessage": "",
    "StatusCode": 200,
    "BrokenRules": []
  },
  "permit": {
    "Result": {
      "PermitId": "b20efcdf-3359-4e49-afc9-4dfb61a68e49",
      "PermitNumber": "RBPR-144560-2025",
      "PermitType": "Residential - New One- and Two-Family Dwelling",
      "PermitStatus": "Issued",
      "IssueDate": "2025-04-22T12:34:00Z",
      "ExpireDate": "2026-08-31T17:12:27Z",
      "FinalizeDate": null,
      "ApplyDate": "2025-04-07T15:04:40.243Z",
      "WorkClassName": "New One- and Two-Family Dwelling",
      "Description": "Kalas Falls PH 1, Lot 28 - 2 Story Single-Family Home  on Crawlspace, 3133 Sq Ft Conditioned Space with 438 Sq Ft Garage, 4 Bedroom(s), 3 Bath(s), Front & Rear Porch, No Deck, 1 Fireplace(s), Note: [none]",
      "IVRNumber": "250384",
      "MainAddress": "1132 DARTFORD GREEN PL \r\nWAKE FOREST, 27587",
      "MainParcelNumber": "1767390585",
      "AssignedTo": "Bower, Rose",
      "AssignedToEmail": "rbower@rolesvillenc.gov",
      "ProjectName": null,
      "DistrictName": "Rolesville",
      "SquareFeet": 0,
      "Value": 665000,
      "LayoutId": "9b9d342e-4b56-452e-8913-1a44c4a37b4c",
      "OnlineLayoutId": "35d11679-c986-4d52-8f5e-2cb1101b6805",
      "ShowSquareFeet": false,
      "ShowValue": true,
      "PermitTypeId": "3921e2e6-5d4b-4aad-89b3-212319bf789e",
      "PermitWorkClassId": "0b63d11c-11a2-481f-94e2-bc312dedb337",
      "PermitTypeWorkClassId": "2ba89f34-334d-4d38-84a4-50c5c838eb97",
      "HoldExistOnInspection": false,
      "UnPaidInvoicedFees": false,
      "UnPaidFees": false,
      "FailedReviews": false,
      "FailedInspections": false,
      "HoldExist": true,
      "Issued": true,
      "IsLoggedIn": false,
      "CanViewSubmittal": false,
      "AllowPayNow": false,
      "HasInvoiceIssue": false,
      "UnpaidInvoiceIds": [],
      "UnpaidPendingInvoiceIds": [],
      "HasAuthorizedContact": false,
      "EReviewEnable": false,
      "MainAddressInfo": {
        "ParentAddressID": null,
        "ParentID": null,
        "MailingAddressID": "03cef1a2-5ffe-4531-b5c0-a5a0575b16b0",
        "CountryType": 0,
        "AddressType": "Location",
        "AddressSystemType": null,
        "Main": false,
        "AddressLine1": "1132",
        "AddressLine2": "DARTFORD GREEN",
        "AddressLine3": "",
        "City": "WAKE FOREST",
        "State": "",
        "County": null,
        "Country": null,
        "PostalCode": "27587",
        "PreDirection": "",
        "PostDirection": "",
        "StreetType": "PL",
        "ParcelID": null,
        "ParcelNumber": null,
        "ParcelAddressID": null,
        "RowVersion": 0,
        "GisAddressId": null,
        "LastChangedOn": null,
        "LastChangedBy": null,
        "AddressDisplay": null,
        "UnitOrSuite": "",
        "Province": "",
        "POBox": null,
        "CompSite": null,
        "RuralRoute": null,
        "Station": null,
        "ATTN": null,
        "GeneralDelivery": false,
        "Range": null,
        "Section": null,
        "Township": null,
        "IsParcel": false,
        "Associated": null,
        "FormattedAddressString": null,
        "AddressProtected": false,
        "IsNew": false,
        "IsDeleted": false,
        "ClientId": null
      },
      "InternetApplicationTypeId": 1,
      "IsEReviewCaseType": false,
      "IsBillingContact": false,
      "DisallowAttachmentAfterApplication": false,
      "PreventRequestInspection": false,
      "EntityHolds": null,
      "ProjectId": null,
      "PermitTypeFilesResubmitTypeId": 1
    },
    "Success": true,
    "ErrorMessage": "",
    "ValidationErrorMessage": "",
    "ConcurrencyErrorMessage": "",
    "StatusCode": 200,
    "BrokenRules": []
  },
  "summary": {
    "Result": [
      {
        "Id": "6c76d73f-32d8-4907-a72e-cb24fc088dc5",
        "Name": "Issue Permit",
        "FriendlyName": "Issue Permit",
        "ActivityType": "CreateReport",
        "ActivityTypeName": "Create Report",
        "ActivityStatusName": null,
        "CompletedOn": null,
        "ScheduledStartDate": null,
        "Status": 0,
        "WorkflowTemplateStepId": "021ebb7a-b3ae-f22d-e75a-122ec4764c64",
        "WorkflowActionTypeId": 13,
        "HearingDate": null,
        "MeetingDate": null,
        "Due": null
      },
      {
        "Id": "c573b4c0-cde0-4799-9a71-2cc80a4dc362",
        "Name": "WM - S&E Control Permit",
        "FriendlyName": "WM - S&E Control Permit",
        "ActivityType": "CreateSubPermit",
        "ActivityTypeName": "Permit",
        "ActivityStatusName": null,
        "CompletedOn": "2022-06-01T15:54:42Z",
        "ScheduledStartDate": null,
        "Status": 0,
        "WorkflowTemplateStepId": "febdc9ca-674e-8004-45e3-2d95f0ab324c",
        "WorkflowActionTypeId": 8,
        "HearingDate": null,
        "MeetingDate": null,
        "Due": null
      },
      {
        "Id": "5daeb4aa-0f4f-4fe1-892e-89cde133432e",
        "Name": "Application Review",
        "FriendlyName": "Application Review",
        "ActivityType": "ReceiveSubmittal",
        "ActivityTypeName": "Submittal",
        "ActivityStatusName": null,
        "CompletedOn": "2025-04-10T04:00:00Z",
        "ScheduledStartDate": null,
        "Status": 0,
        "WorkflowTemplateStepId": "204186c7-df67-779f-ae45-6b472f4724dd",
        "WorkflowActionTypeId": 1,
        "HearingDate": null,
        "MeetingDate": null,
        "Due": null
      },
      {
        "Id": "f5100518-8e1d-472f-a197-f4db903ccada",
        "Name": "Residential Plan Review",
        "FriendlyName": "Residential Plan Review",
        "ActivityType": "ReceiveSubmittal",
        "ActivityTypeName": "Submittal",
        "ActivityStatusName": null,
        "CompletedOn": "2025-04-16T04:00:00Z",
        "ScheduledStartDate": null,
        "Status": 0,
        "WorkflowTemplateStepId": "8ae8ab42-9eb9-96f2-f3c3-eb68b09d073a",
        "WorkflowActionTypeId": 1,
        "HearingDate": null,
        "MeetingDate": null,
        "Due": null
      },
      {
        "Id": "e14ecc0b-825d-4da6-b7b1-8d5d5121984f",
        "Name": "P&I - Footing or Monolithic Slab",
        "FriendlyName": "P&I - Footing or Monolithic Slab",
        "ActivityType": "Inspection",
        "ActivityTypeName": "Inspection",
        "ActivityStatusName": "Passed",
        "CompletedOn": "2025-05-07T13:01:14.057Z",
        "ScheduledStartDate": "2025-05-07T04:00:00Z",
        "Status": 0,
        "WorkflowTemplateStepId": "0bb7b820-6aed-1bf9-8834-3016bbd70e6f",
        "WorkflowActionTypeId": 6,
        "HearingDate": null,
        "MeetingDate": null,
        "Due": null
      },
      {
        "Id": "422dd1cb-e9c0-cd24-1179-7b34e83db84b",
        "Name": "P&I - Foundation",
        "FriendlyName": "P&I - Foundation",
        "ActivityType": "Inspection",
        "ActivityTypeName": "Inspection",
        "ActivityStatusName": "Passed",
        "CompletedOn": "2025-05-08T13:06:15.87Z",
        "ScheduledStartDate": "2025-05-08T04:00:00Z",
        "Status": 0,
        "WorkflowTemplateStepId": "0bb7b820-6aed-1bf9-8834-3016bbd70e6f",
        "WorkflowActionTypeId": 6,
        "HearingDate": null,
        "MeetingDate": null,
        "Due": null
      },
      {
        "Id": "b657be18-a437-2a73-cef3-211c1d502cca",
        "Name": "P&I - Floor Framing",
        "FriendlyName": "P&I - Floor Framing",
        "ActivityType": "Inspection",
        "ActivityTypeName": "Inspection",
        "ActivityStatusName": "Passed",
        "CompletedOn": "2025-05-08T13:12:32.78Z",
        "ScheduledStartDate": "2025-05-08T13:00:00Z",
        "Status": 0,
        "WorkflowTemplateStepId": "0bb7b820-6aed-1bf9-8834-3016bbd70e6f",
        "WorkflowActionTypeId": 6,
        "HearingDate": null,
        "MeetingDate": null,
        "Due": null
      },
      {
        "Id": "67b7324a-dc35-4520-9cae-041858128ab0",
        "Name": "P&I - Plumbing Rough",
        "FriendlyName": "P&I - Plumbing Rough",
        "ActivityType": "Inspection",
        "ActivityTypeName": "Inspection",
        "ActivityStatusName": "Passed",
        "CompletedOn": "2025-05-21T17:38:38.907Z",
        "ScheduledStartDate": "2025-05-21T04:00:00Z",
        "Status": 0,
        "WorkflowTemplateStepId": "0bb7b820-6aed-1bf9-8834-3016bbd70e6f",
        "WorkflowActionTypeId": 6,
        "HearingDate": null,
        "MeetingDate": null,
        "Due": null
      },
      {
        "Id": "f98a1e2a-5fea-400d-a696-169ad91ec420",
        "Name": "P&I - Mechanical Rough",
        "FriendlyName": "P&I - Mechanical Rough",
        "ActivityType": "Inspection",
        "ActivityTypeName": "Inspection",
        "ActivityStatusName": "Re-inspection required with fee - Permit",
        "CompletedOn": "2025-05-22T11:52:09.543Z",
        "ScheduledStartDate": "2025-05-22T04:00:00Z",
        "Status": 3,
        "WorkflowTemplateStepId": "0bb7b820-6aed-1bf9-8834-3016bbd70e6f",
        "WorkflowActionTypeId": 6,
        "HearingDate": null,
        "MeetingDate": null,
        "Due": null
      },
      {
        "Id": "bfd1c695-1f7a-400b-84ca-a115e984d7f8",
        "Name": "P&I - Mechanical Rough",
        "FriendlyName": "P&I - Mechanical Rough",
        "ActivityType": "Inspection",
        "ActivityTypeName": "Inspection",
        "ActivityStatusName": "Passed",
        "CompletedOn": "2025-05-23T17:41:48.007Z",
        "ScheduledStartDate": "2025-05-23T04:00:00Z",
        "Status": 0,
        "WorkflowTemplateStepId": "0bb7b820-6aed-1bf9-8834-3016bbd70e6f",
        "WorkflowActionTypeId": 6,
        "HearingDate": null,
        "MeetingDate": null,
        "Due": null
      },
      {
        "Id": "08571df5-fd9f-4f31-8f85-dd83926e91dd",
        "Name": "P&I - Electrical Rough",
        "FriendlyName": "P&I - Electrical Rough",
        "ActivityType": "Inspection",
        "ActivityTypeName": "Inspection",
        "ActivityStatusName": "Passed",
        "CompletedOn": "2025-05-27T15:32:41.817Z",
        "ScheduledStartDate": "2025-05-27T04:00:00Z",
        "Status": 0,
        "WorkflowTemplateStepId": "0bb7b820-6aed-1bf9-8834-3016bbd70e6f",
        "WorkflowActionTypeId": 6,
        "HearingDate": null,
        "MeetingDate": null,
        "Due": null
      },
      {
        "Id": "04fc0cf6-1b01-4806-9cea-0e0e98d85338",
        "Name": "P&I - Framing",
        "FriendlyName": "P&I - Framing",
        "ActivityType": "Inspection",
        "ActivityTypeName": "Inspection",
        "ActivityStatusName": "Passed with Conditions",
        "CompletedOn": "2025-05-28T14:41:15.607Z",
        "ScheduledStartDate": "2025-05-28T04:00:00Z",
        "Status": 0,
        "WorkflowTemplateStepId": "0bb7b820-6aed-1bf9-8834-3016bbd70e6f",
        "WorkflowActionTypeId": 6,
        "HearingDate": null,
        "MeetingDate": null,
        "Due": null
      },
      {
        "Id": "489f7156-27b3-4958-8f7c-d0f9167dde08",
        "Name": "P&I - Insulation",
        "FriendlyName": "P&I - Insulation",
        "ActivityType": "Inspection",
        "ActivityTypeName": "Inspection",
        "ActivityStatusName": "Re-inspection required with fee - Permit",
        "CompletedOn": "2025-06-04T17:18:21.577Z",
        "ScheduledStartDate": "2025-06-04T04:00:00Z",
        "Status": 3,
        "WorkflowTemplateStepId": "0bb7b820-6aed-1bf9-8834-3016bbd70e6f",
        "WorkflowActionTypeId": 6,
        "HearingDate": null,
        "MeetingDate": null,
        "Due": null
      },
      {
        "Id": "9eaa4af1-169b-4e54-9041-a87c911e8333",
        "Name": "P&I - Insulation",
        "FriendlyName": "P&I - Insulation",
        "ActivityType": "Inspection",
        "ActivityTypeName": "Inspection",
        "ActivityStatusName": "Passed",
        "CompletedOn": "2025-06-06T14:43:56.893Z",
        "ScheduledStartDate": "2025-06-06T04:00:00Z",
        "Status": 0,
        "WorkflowTemplateStepId": "0bb7b820-6aed-1bf9-8834-3016bbd70e6f",
        "WorkflowActionTypeId": 6,
        "HearingDate": null,
        "MeetingDate": null,
        "Due": null
      },
      {
        "Id": "cd4e67d2-184b-4f4f-b027-ae70f67f4346",
        "Name": "P&I - Water Connection",
        "FriendlyName": "P&I - Water Connection",
        "ActivityType": "Inspection",
        "ActivityTypeName": "Inspection",
        "ActivityStatusName": "Passed",
        "CompletedOn": "2025-06-20T18:56:19.22Z",
        "ScheduledStartDate": "2025-06-20T04:00:00Z",
        "Status": 0,
        "WorkflowTemplateStepId": "0bb7b820-6aed-1bf9-8834-3016bbd70e6f",
        "WorkflowActionTypeId": 6,
        "HearingDate": null,
        "MeetingDate": null,
        "Due": null
      },
      {
        "Id": "fe435662-5f5d-42d8-8ea0-d87892e46365",
        "Name": "P&I - Sewer Connection",
        "FriendlyName": "P&I - Sewer Connection",
        "ActivityType": "Inspection",
        "ActivityTypeName": "Inspection",
        "ActivityStatusName": "Passed",
        "CompletedOn": "2025-06-20T18:56:19.22Z",
        "ScheduledStartDate": "2025-06-20T04:00:00Z",
        "Status": 0,
        "WorkflowTemplateStepId": "0bb7b820-6aed-1bf9-8834-3016bbd70e6f",
        "WorkflowActionTypeId": 6,
        "HearingDate": null,
        "MeetingDate": null,
        "Due": null
      },
      {
        "Id": "75a00d12-9d4f-47d6-a5bb-f1292794fd24",
        "Name": "P&I - Plumbing Groundwork",
        "FriendlyName": "P&I - Plumbing Groundwork",
        "ActivityType": "Inspection",
        "ActivityTypeName": "Inspection",
        "ActivityStatusName": "Passed",
        "CompletedOn": "2025-06-20T18:56:19.23Z",
        "ScheduledStartDate": "2025-06-20T04:00:00Z",
        "Status": 0,
        "WorkflowTemplateStepId": "0bb7b820-6aed-1bf9-8834-3016bbd70e6f",
        "WorkflowActionTypeId": 6,
        "HearingDate": null,
        "MeetingDate": null,
        "Due": null
      },
      {
        "Id": "b163a8e1-87ac-4820-8c1e-9e619fedcfee",
        "Name": "P&I - Sewer Connection",
        "FriendlyName": "P&I - Sewer Connection",
        "ActivityType": "Inspection",
        "ActivityTypeName": "Inspection",
        "ActivityStatusName": "Passed",
        "CompletedOn": "2025-06-20T18:56:19.23Z",
        "ScheduledStartDate": "2025-06-20T04:00:00Z",
        "Status": 0,
        "WorkflowTemplateStepId": "0bb7b820-6aed-1bf9-8834-3016bbd70e6f",
        "WorkflowActionTypeId": 6,
        "HearingDate": null,
        "MeetingDate": null,
        "Due": null
      },
      {
        "Id": "99b8b984-4081-4d67-8189-db8f6cd4f357",
        "Name": "P&I - Electrical Final",
        "FriendlyName": "P&I - Electrical Final",
        "ActivityType": "Inspection",
        "ActivityTypeName": "Inspection",
        "ActivityStatusName": "Passed",
        "CompletedOn": "2025-07-11T12:48:05.533Z",
        "ScheduledStartDate": "2025-07-11T04:00:00Z",
        "Status": 0,
        "WorkflowTemplateStepId": "0bb7b820-6aed-1bf9-8834-3016bbd70e6f",
        "WorkflowActionTypeId": 6,
        "HearingDate": null,
        "MeetingDate": null,
        "Due": null
      },
      {
        "Id": "aa54ab85-9695-4131-939c-fac1e178ff47",
        "Name": "P&I - Mechanical Final",
        "FriendlyName": "P&I - Mechanical Final",
        "ActivityType": "Inspection",
        "ActivityTypeName": "Inspection",
        "ActivityStatusName": "Passed",
        "CompletedOn": "2025-07-11T13:02:53.59Z",
        "ScheduledStartDate": "2025-07-11T04:00:00Z",
        "Status": 0,
        "WorkflowTemplateStepId": "0bb7b820-6aed-1bf9-8834-3016bbd70e6f",
        "WorkflowActionTypeId": 6,
        "HearingDate": null,
        "MeetingDate": null,
        "Due": null
      },
      {
        "Id": "44f42cdf-ebcc-4a47-a5cf-da3609061c14",
        "Name": "P&I - Plumbing Final",
        "FriendlyName": "P&I - Plumbing Final",
        "ActivityType": "Inspection",
        "ActivityTypeName": "Inspection",
        "ActivityStatusName": "Passed",
        "CompletedOn": "2025-07-14T12:22:55.2Z",
        "ScheduledStartDate": "2025-07-14T04:00:00Z",
        "Status": 0,
        "WorkflowTemplateStepId": "0bb7b820-6aed-1bf9-8834-3016bbd70e6f",
        "WorkflowActionTypeId": 6,
        "HearingDate": null,
        "MeetingDate": null,
        "Due": null
      },
      {
        "Id": "dfa19df5-234e-485d-a49a-feadb10a1e31",
        "Name": "P&I - Building Final",
        "FriendlyName": "P&I - Building Final",
        "ActivityType": "Inspection",
        "ActivityTypeName": "Inspection",
        "ActivityStatusName": "Passed",
        "CompletedOn": "2025-08-29T17:12:45.443Z",
        "ScheduledStartDate": "2025-08-29T04:00:00Z",
        "Status": 0,
        "WorkflowTemplateStepId": "0bb7b820-6aed-1bf9-8834-3016bbd70e6f",
        "WorkflowActionTypeId": 6,
        "HearingDate": null,
        "MeetingDate": null,
        "Due": null
      },
      {
        "Id": "54ec35f9-9c89-4928-8f40-19eca7843bf3",
        "Name": "Notify Utility Companies",
        "FriendlyName": "Notify Utility Companies",
        "ActivityType": "GenericAction",
        "ActivityTypeName": "Generic Action",
        "ActivityStatusName": null,
        "CompletedOn": null,
        "ScheduledStartDate": null,
        "Status": 1,
        "WorkflowTemplateStepId": "858b38d8-eec4-2dd6-3d77-560c444e0cee",
        "WorkflowActionTypeId": 5,
        "HearingDate": null,
        "MeetingDate": null,
        "Due": null
      },
      {
        "Id": "dc02d61a-154a-441b-a26a-899b82c39033",
        "Name": "Issue CO",
        "FriendlyName": "Issue CO",
        "ActivityType": "CreateReport",
        "ActivityTypeName": "Create Report",
        "ActivityStatusName": null,
        "CompletedOn": null,
        "ScheduledStartDate": null,
        "Status": 1,
        "WorkflowTemplateStepId": "858b38d8-eec4-2dd6-3d77-560c444e0cee",
        "WorkflowActionTypeId": 13,
        "HearingDate": null,
        "MeetingDate": null,
        "Due": null
      }
    ],
    "Success": true,
    "ErrorMessage": "",
    "ValidationErrorMessage": "",
    "ConcurrencyErrorMessage": "",
    "StatusCode": 200,
    "BrokenRules": []
  }
}